RPi/__init__.py
RPi/version.py
RPi.version-2.0.dist-info/METADATA
RPi.version-2.0.dist-info/WHEEL
RPi.version-2.0.dist-info/entry_points.txt
RPi.version-2.0.dist-info/top_level.txt
RPi.version-2.0.dist-info/RECORD
